openfisca_tunisia_pension/__init__.py
openfisca_tunisia_pension/entities.py
openfisca_tunisia_pension/tools.py
openfisca_tunisia_pension/units.yaml
openfisca_tunisia_pension/doc/Tableau synoptique Régimes tunisiens SS.doc
openfisca_tunisia_pension/doc/Taux de cotisation CNSS ET CNRPS.xlsx
openfisca_tunisia_pension/parameters/marche_travail/indemnite_complementaire_provisoire.yaml
openfisca_tunisia_pension/parameters/marche_travail/index.yaml
openfisca_tunisia_pension/parameters/marche_travail/majoration_smig_40h_mensuel.yaml
openfisca_tunisia_pension/parameters/marche_travail/majoration_smig_48h_mensuel.yaml
openfisca_tunisia_pension/parameters/marche_travail/salaire_de_base_40h_horaire.yaml
openfisca_tunisia_pension/parameters/marche_travail/salaire_de_base_40h_mensuel.yaml
openfisca_tunisia_pension/parameters/marche_travail/salaire_de_base_48h_horaire.yaml
openfisca_tunisia_pension/parameters/marche_travail/salaire_de_base_48h_mensuel.yaml
openfisca_tunisia_pension/parameters/marche_travail/smag_journalier.yaml
openfisca_tunisia_pension/parameters/marche_travail/smig_40h_horaire.yaml
openfisca_tunisia_pension/parameters/marche_travail/smig_40h_mensuel.yaml
openfisca_tunisia_pension/parameters/marche_travail/smig_48h_horaire.yaml
openfisca_tunisia_pension/parameters/marche_travail/smig_48h_mensuel.yaml
openfisca_tunisia_pension/parameters/retraite/index.yaml
openfisca_tunisia_pension/parameters/retraite/cnrps/bareme_annuite.yaml
openfisca_tunisia_pension/parameters/retraite/cnrps/duree_de_service_minimale.yaml
openfisca_tunisia_pension/parameters/retraite/cnrps/age_legal/index.yaml
openfisca_tunisia_pension/parameters/retraite/cnrps/age_legal/civil/cadre_commun.yaml
openfisca_tunisia_pension/parameters/retraite/cnrps/age_legal/civil/cadres_actifs.yaml
openfisca_tunisia_pension/parameters/retraite/cnrps/age_legal/civil/enseignants_du_superieur.yaml
openfisca_tunisia_pension/parameters/retraite/cnrps/age_legal/civil/index.yaml
OpenFisca_Tunisia_Pension-5.0.0.dist-info/LICENSE
OpenFisca_Tunisia_Pension-5.0.0.dist-info/METADATA
OpenFisca_Tunisia_Pension-5.0.0.dist-info/WHEEL
OpenFisca_Tunisia_Pension-5.0.0.dist-info/top_level.txt
OpenFisca_Tunisia_Pension-5.0.0.dist-info/RECORD
